alchemyrohan-0.5.0.dist-info/METADATA
alchemyrohan-0.5.0.dist-info/WHEEL
alchemyrohan-0.5.0.dist-info/entry_points.txt
alchemyrohan-0.5.0.dist-info/licenses/LICENSE
alchemyrohan/__init__.py
alchemyrohan/assemble.py
alchemyrohan/meta_data.py
alchemyrohan/oracle.py
alchemyrohan/sqlite.py
alchemyrohan/utils.py
alchemyrohan/wizard.py
alchemyrohan-0.5.0.dist-info/RECORD
