Metadata-Version: 2.1
Name: alchemyrohan
Version: 0.5.0
Summary: Is a helpful tool for creating SqlAlchemy models.
Keywords: alchemyrohan,database,SQLAlchemy,models,help-tool
Author-Email: Alan Wamberger <awamberger@proton.me>
License: MIT License
Classifier: Development Status :: 4 - Beta
Classifier: Intended Audience :: Developers
Classifier: License :: OSI Approved :: MIT License
Classifier: Natural Language :: English
Classifier: Operating System :: OS Independent
Classifier: Programming Language :: Python :: 3
Classifier: Programming Language :: Python :: 3.10
Classifier: Programming Language :: Python :: 3.11
Classifier: Programming Language :: Python :: 3.12
Classifier: Topic :: Software Development :: Code Generators
Project-URL: Homepage, https://github.com/wamberger/alchemyrohan
Project-URL: Documentation, https://github.com/wamberger/alchemyrohan/blob/master/README.md
Project-URL: Repository, https://github.com/wamberger/alchemyrohan
Project-URL: Changelog, https://github.com/wamberger/alchemyrohan/blob/master/CHANGELOG.md
Requires-Python: >=3.10
Requires-Dist: SQLAlchemy>=2.0.29
Requires-Dist: oracledb>=2.1.1
